{"_id":"vega-embed","_rev":"35-a54553c5edf509b325b5997f516c0f15","name":"vega-embed","description":"Publish Vega visualizations as embedded web components.","dist-tags":{"latest":"3.0.0-beta.20","pre":"3.0.0-beta.11"},"versions":{"1.0.0":{"name":"vega-embed","version":"1.0.0","description":"Publish Vega visualizations as embedded web components.","keywords":["vega","data","visualization","component","embed"],"repository":{"type":"git","url":"git+ssh://git@github.com/vega/vega-embed.git"},"author":{"name":"Jeffrey Heer","url":"http://idl.cs.washington.edu"},"license":"BSD-3-Clause","devDependencies":{"d3":"^3.5.6","topojson":"^1.6.19","vega":"^2.1.1","browserify":"^10.2.6","browserify-shim":"^3.8.9","jshint":"^2.8.0","uglify-js":"^2.4.24"},"scripts":{"deploy":"npm run lint && scripts/deploy.sh","lint":"jshint src/","build":"browserify src/embed.js -d -s vg.embed > vega-embed.js","postbuild":"uglifyjs vega-embed.js -cm > vega-embed.min.js"},"browserify":{"transform":["browserify-shim"]},"browserify-shim":{"d3":"global:d3","vega":"global:vg"},"gitHead":"a8a4345b8b23c33269ff873319d709e2ea62556b","bugs":{"url":"https://github.com/vega/vega-embed/issues"},"homepage":"https://github.com/vega/vega-embed#readme","_id":"vega-embed@1.0.0","_shasum":"4336cff245574c516d45e7451ef7259ba7ba6337","_from":".","_npmVersion":"2.12.1","_nodeVersion":"0.12.7","_npmUser":{"name":"jheer","email":"jeffrey.heer@gmail.com"},"maintainers":[{"name":"jheer","email":"jeffrey.heer@gmail.com"}],"dist":{"shasum":"4336cff245574c516d45e7451ef7259ba7ba6337","tarball":"https://registry.npmjs.org/vega-embed/-/vega-embed-1.0.0.tgz"},"directories":{}},"1.0.1":{"name":"vega-embed","version":"1.0.1","description":"Publish Vega visualizations as embedded web components.","keywords":["vega","data","visualization","component","embed"],"repository":{"type":"git","url":"git+ssh://git@github.com/vega/vega-embed.git"},"author":{"name":"Jeffrey Heer","url":"http://idl.cs.washington.edu"},"license":"BSD-3-Clause","devDependencies":{"d3":"^3.5.6","topojson":"^1.6.19","vega":"^2.1.1","browserify":"^10.2.6","browserify-shim":"^3.8.9","jshint":"^2.8.0","uglify-js":"^2.4.24"},"scripts":{"deploy":"npm run lint && scripts/deploy.sh","lint":"jshint src/","build":"browserify src/embed.js -d -s vg.embed > vega-embed.js","postbuild":"uglifyjs vega-embed.js -cm > vega-embed.min.js"},"browserify":{"transform":["browserify-shim"]},"browserify-shim":{"d3":"global:d3","vega":"global:vg"},"gitHead":"d6aafe3c852e1fea88c32eab7c4ce158d0fddd19","bugs":{"url":"https://github.com/vega/vega-embed/issues"},"homepage":"https://github.com/vega/vega-embed#readme","_id":"vega-embed@1.0.1","_shasum":"32d5f5c296ef649b419c4d218912469048630b25","_from":".","_npmVersion":"2.12.1","_nodeVersion":"0.12.7","_npmUser":{"name":"jheer","email":"jeffrey.heer@gmail.com"},"maintainers":[{"name":"jheer","email":"jeffrey.heer@gmail.com"}],"dist":{"shasum":"32d5f5c296ef649b419c4d218912469048630b25","tarball":"https://registry.npmjs.org/vega-embed/-/vega-embed-1.0.1.tgz"},"directories":{}},"1.0.2":{"name":"vega-embed","version":"1.0.2","description":"Publish Vega visualizations as embedded web components.","keywords":["vega","data","visualization","component","embed"],"repository":{"type":"git","url":"git+ssh://git@github.com/vega/vega-embed.git"},"author":{"name":"Jeffrey Heer","url":"http://idl.cs.washington.edu"},"license":"BSD-3-Clause","devDependencies":{"d3":"^3.5.6","topojson":"^1.6.19","vega":"^2.1.1","browserify":"^10.2.6","browserify-shim":"^3.8.9","jshint":"^2.8.0","uglify-js":"^2.4.24"},"scripts":{"deploy":"npm run lint && scripts/deploy.sh","lint":"jshint src/","build":"browserify src/embed.js -d -s vg.embed > vega-embed.js","postbuild":"uglifyjs vega-embed.js -cm > vega-embed.min.js"},"browserify":{"transform":["browserify-shim"]},"browserify-shim":{"d3":"global:d3","vega":"global:vg"},"gitHead":"e67971b639fbbc5f783b75718c5c9c75de7081b8","bugs":{"url":"https://github.com/vega/vega-embed/issues"},"homepage":"https://github.com/vega/vega-embed#readme","_id":"vega-embed@1.0.2","_shasum":"13fd8e88495541a0ec74fc8bdd69d959cd7961f8","_from":".","_npmVersion":"2.12.1","_nodeVersion":"0.12.7","_npmUser":{"name":"jheer","email":"jeffrey.heer@gmail.com"},"maintainers":[{"name":"jheer","email":"jeffrey.heer@gmail.com"}],"dist":{"shasum":"13fd8e88495541a0ec74fc8bdd69d959cd7961f8","tarball":"https://registry.npmjs.org/vega-embed/-/vega-embed-1.0.2.tgz"},"directories":{}},"1.0.3":{"name":"vega-embed","version":"1.0.3","description":"Publish Vega visualizations as embedded web components.","keywords":["vega","data","visualization","component","embed"],"repository":{"type":"git","url":"git+ssh://git@github.com/vega/vega-embed.git"},"author":{"name":"Jeffrey Heer","url":"http://idl.cs.washington.edu"},"license":"BSD-3-Clause","devDependencies":{"d3":"^3.5.6","d3-geo-projection":"^0.2.15","topojson":"^1.6.19","vega":"^2.1.1","browserify":"^10.2.6","browserify-shim":"^3.8.9","jshint":"^2.8.0","uglify-js":"^2.4.24"},"scripts":{"deploy":"npm run lint && scripts/deploy.sh","lint":"jshint src/","build":"browserify src/embed.js -d -s vg.embed > vega-embed.js","postbuild":"uglifyjs vega-embed.js -cm > vega-embed.min.js"},"browserify":{"transform":["browserify-shim"]},"browserify-shim":{"d3":"global:d3","vega":"global:vg"},"gitHead":"9ef745d577b43db9fdba1ab61eb3e8db95a75d5d","bugs":{"url":"https://github.com/vega/vega-embed/issues"},"homepage":"https://github.com/vega/vega-embed#readme","_id":"vega-embed@1.0.3","_shasum":"2f5a8108e3e311e169c38bcff539d3a0b48022a0","_from":".","_npmVersion":"2.12.1","_nodeVersion":"0.12.7","_npmUser":{"name":"jheer","email":"jeffrey.heer@gmail.com"},"maintainers":[{"name":"jheer","email":"jeffrey.heer@gmail.com"}],"dist":{"shasum":"2f5a8108e3e311e169c38bcff539d3a0b48022a0","tarball":"https://registry.npmjs.org/vega-embed/-/vega-embed-1.0.3.tgz"},"directories":{}},"1.0.4":{"name":"vega-embed","version":"1.0.4","description":"Publish Vega visualizations as embedded web components.","keywords":["vega","data","visualization","component","embed"],"repository":{"type":"git","url":"git+ssh://git@github.com/vega/vega-embed.git"},"author":{"name":"Jeffrey Heer","url":"http://idl.cs.washington.edu"},"license":"BSD-3-Clause","devDependencies":{"d3":"^3.5.6","d3-geo-projection":"^0.2.15","topojson":"^1.6.19","vega":"^2.2.0","browserify":"^10.2.6","browserify-shim":"^3.8.9","chai":"^3.0.0","jshint":"^2.8.0","mocha":"^2.2.5","tv4":"^1.1.12","uglify-js":"^2.4.24"},"scripts":{"deploy":"npm run lint && scripts/deploy.sh","lint":"jshint src/","test":"npm run schema && mocha --timeout 5000 --recursive test/","build":"browserify src/embed.js -d -s vg.embed > vega-embed.js","postbuild":"uglifyjs vega-embed.js -cm > vega-embed.min.js","schema":"node scripts/schema.js > vega-embed-schema.json"},"browserify":{"transform":["browserify-shim"]},"browserify-shim":{"d3":"global:d3","vega":"global:vg"},"gitHead":"c126b2fa75ba5ddc6f7029919090828dd15fbead","bugs":{"url":"https://github.com/vega/vega-embed/issues"},"homepage":"https://github.com/vega/vega-embed#readme","_id":"vega-embed@1.0.4","_shasum":"cca0443917753dc24bc99bbf1921093f558bf2b7","_from":".","_npmVersion":"2.12.1","_nodeVersion":"0.12.7","_npmUser":{"name":"jheer","email":"jeffrey.heer@gmail.com"},"maintainers":[{"name":"jheer","email":"jeffrey.heer@gmail.com"}],"dist":{"shasum":"cca0443917753dc24bc99bbf1921093f558bf2b7","tarball":"https://registry.npmjs.org/vega-embed/-/vega-embed-1.0.4.tgz"},"directories":{}},"1.0.5":{"name":"vega-embed","version":"1.0.5","description":"Publish Vega visualizations as embedded web components.","keywords":["vega","data","visualization","component","embed"],"repository":{"type":"git","url":"git+ssh://git@github.com/vega/vega-embed.git"},"author":{"name":"Jeffrey Heer","url":"http://idl.cs.washington.edu"},"license":"BSD-3-Clause","devDependencies":{"d3":"^3.5.6","d3-geo-projection":"^0.2.15","topojson":"^1.6.19","vega":"^2.2.0","browserify":"^10.2.6","browserify-shim":"^3.8.9","chai":"^3.0.0","jshint":"^2.8.0","mocha":"^2.2.5","tv4":"^1.1.12","uglify-js":"^2.4.24"},"scripts":{"deploy":"npm run lint && npm run test && scripts/deploy.sh","lint":"jshint src/","test":"npm run schema && mocha --timeout 5000 --recursive test/","build":"browserify src/embed.js -d -s vg.embed > vega-embed.js","postbuild":"uglifyjs vega-embed.js -cm > vega-embed.min.js","schema":"node scripts/schema.js > vega-embed-schema.json"},"browserify":{"transform":["browserify-shim"]},"browserify-shim":{"d3":"global:d3","vega":"global:vg"},"gitHead":"19ab1ca553f3cf7479fd8995dde21fa89b62606d","bugs":{"url":"https://github.com/vega/vega-embed/issues"},"homepage":"https://github.com/vega/vega-embed#readme","_id":"vega-embed@1.0.5","_shasum":"d6c043332f2a59a423e0c6f02be5e661ae899780","_from":".","_npmVersion":"2.12.1","_nodeVersion":"0.12.7","_npmUser":{"name":"jheer","email":"jeffrey.heer@gmail.com"},"maintainers":[{"name":"jheer","email":"jeffrey.heer@gmail.com"}],"dist":{"shasum":"d6c043332f2a59a423e0c6f02be5e661ae899780","tarball":"https://registry.npmjs.org/vega-embed/-/vega-embed-1.0.5.tgz"},"directories":{}},"1.0.6":{"name":"vega-embed","version":"1.0.6","description":"Publish Vega visualizations as embedded web components.","keywords":["vega","data","visualization","component","embed"],"repository":{"type":"git","url":"git+ssh://git@github.com/vega/vega-embed.git"},"author":{"name":"Jeffrey Heer","url":"http://idl.cs.washington.edu"},"license":"BSD-3-Clause","devDependencies":{"d3":"^3.5.6","d3-geo-projection":"^0.2.15","topojson":"^1.6.19","vega":"^2.2.0","browserify":"^10.2.6","browserify-shim":"^3.8.9","chai":"^3.0.0","jshint":"^2.8.0","mocha":"^2.2.5","tv4":"^1.1.12","uglify-js":"^2.4.24"},"scripts":{"deploy":"npm run lint && npm run test && scripts/deploy.sh","lint":"jshint src/","test":"npm run schema && mocha --timeout 5000 --recursive test/","build":"browserify src/embed.js -d -s vg.embed > vega-embed.js","postbuild":"uglifyjs vega-embed.js -cm > vega-embed.min.js","schema":"node scripts/schema.js > vega-embed-schema.json"},"browserify":{"transform":["browserify-shim"]},"browserify-shim":{"d3":"global:d3","vega":"global:vg"},"gitHead":"de3a821bc26c21299c514bc88bcadff5fdb2ebdc","bugs":{"url":"https://github.com/vega/vega-embed/issues"},"homepage":"https://github.com/vega/vega-embed#readme","_id":"vega-embed@1.0.6","_shasum":"416115c4e5c3c53ae3a5ac3a5ab3824b6bb870a2","_from":".","_npmVersion":"2.12.1","_nodeVersion":"0.12.7","_npmUser":{"name":"jheer","email":"jeffrey.heer@gmail.com"},"maintainers":[{"name":"jheer","email":"jeffrey.heer@gmail.com"}],"dist":{"shasum":"416115c4e5c3c53ae3a5ac3a5ab3824b6bb870a2","tarball":"https://registry.npmjs.org/vega-embed/-/vega-embed-1.0.6.tgz"},"directories":{}},"1.0.7":{"name":"vega-embed","version":"1.0.7","description":"Publish Vega visualizations as embedded web components.","keywords":["vega","data","visualization","component","embed"],"repository":{"type":"git","url":"git+ssh://git@github.com/vega/vega-embed.git"},"author":{"name":"Jeffrey Heer","url":"http://idl.cs.washington.edu"},"license":"BSD-3-Clause","devDependencies":{"d3":"^3.5.6","d3-geo-projection":"^0.2.15","topojson":"^1.6.19","vega":"^2.2.0","browserify":"^10.2.6","browserify-shim":"^3.8.9","chai":"^3.0.0","jshint":"^2.8.0","mocha":"^2.2.5","tv4":"^1.1.12","uglify-js":"^2.4.24"},"scripts":{"deploy":"npm run lint && npm run test && scripts/deploy.sh","lint":"jshint src/","test":"npm run schema && mocha --timeout 5000 --recursive test/","build":"browserify src/embed.js -d -s vg.embed > vega-embed.js","postbuild":"uglifyjs vega-embed.js -cm > vega-embed.min.js","schema":"node scripts/schema.js > vega-embed-schema.json"},"browserify":{"transform":["browserify-shim"]},"browserify-shim":{"d3":"global:d3","vega":"global:vg"},"gitHead":"7f78115ada6da3e99d39051183da02d8f96384ce","bugs":{"url":"https://github.com/vega/vega-embed/issues"},"homepage":"https://github.com/vega/vega-embed#readme","_id":"vega-embed@1.0.7","_shasum":"0864787d82131ed2280abdec6c2ef3749ad532b3","_from":".","_npmVersion":"2.12.1","_nodeVersion":"0.12.7","_npmUser":{"name":"jheer","email":"jeffrey.heer@gmail.com"},"maintainers":[{"name":"jheer","email":"jeffrey.heer@gmail.com"}],"dist":{"shasum":"0864787d82131ed2280abdec6c2ef3749ad532b3","tarball":"https://registry.npmjs.org/vega-embed/-/vega-embed-1.0.7.tgz"},"directories":{}},"1.0.8":{"name":"vega-embed","version":"1.0.8","description":"Publish Vega visualizations as embedded web components.","keywords":["vega","data","visualization","component","embed"],"repository":{"type":"git","url":"git+ssh://git@github.com/vega/vega-embed.git"},"author":{"name":"Jeffrey Heer","url":"http://idl.cs.washington.edu"},"license":"BSD-3-Clause","devDependencies":{"d3":"^3.5.6","d3-geo-projection":"^0.2.15","topojson":"^1.6.19","vega":"^2.2.3","browserify":"^10.2.6","browserify-shim":"^3.8.9","chai":"^3.0.0","jshint":"^2.8.0","mocha":"^2.2.5","tv4":"^1.1.12","uglify-js":"^2.4.24"},"scripts":{"deploy":"npm run lint && npm run test && scripts/deploy.sh","lint":"jshint src/","test":"npm run schema && mocha --timeout 5000 --recursive test/","build":"browserify src/embed.js -d -s vg.embed > vega-embed.js","postbuild":"uglifyjs vega-embed.js -cm > vega-embed.min.js","schema":"node scripts/schema.js > vega-embed-schema.json","watch":"watchify src/embed.js -v -d -s vg.embed -o vega-embed.js"},"browserify":{"transform":["browserify-shim"]},"browserify-shim":{"d3":"global:d3","vega":"global:vg"},"gitHead":"c924c60ccf5594b03b28a5c7e64a1c3c35614e6c","bugs":{"url":"https://github.com/vega/vega-embed/issues"},"homepage":"https://github.com/vega/vega-embed#readme","_id":"vega-embed@1.0.8","_shasum":"44bec316a8eafe62382a4c339dbc63e46011f768","_from":".","_npmVersion":"2.12.1","_nodeVersion":"0.12.7","_npmUser":{"name":"jheer","email":"jeffrey.heer@gmail.com"},"maintainers":[{"name":"jheer","email":"jeffrey.heer@gmail.com"}],"dist":{"shasum":"44bec316a8eafe62382a4c339dbc63e46011f768","tarball":"https://registry.npmjs.org/vega-embed/-/vega-embed-1.0.8.tgz"},"directories":{}},"1.0.9":{"name":"vega-embed","version":"1.0.9","description":"Publish Vega visualizations as embedded web components.","keywords":["vega","data","visualization","component","embed"],"repository":{"type":"git","url":"git+ssh://git@github.com/vega/vega-embed.git"},"author":{"name":"Jeffrey Heer","url":"http://idl.cs.washington.edu"},"license":"BSD-3-Clause","devDependencies":{"d3":"^3.5.6","d3-geo-projection":"^0.2.15","topojson":"^1.6.19","vega":"^2.2.4","browserify":"^10.2.6","browserify-shim":"^3.8.9","chai":"^3.0.0","jshint":"^2.8.0","mocha":"^2.2.5","tv4":"^1.1.12","uglify-js":"^2.4.24"},"scripts":{"deploy":"npm run lint && npm run test && scripts/deploy.sh","lint":"jshint src/","test":"npm run schema && mocha --timeout 5000 --recursive test/","build":"browserify src/embed.js -d -s vg.embed > vega-embed.js","postbuild":"uglifyjs vega-embed.js -cm > vega-embed.min.js","schema":"node scripts/schema.js > vega-embed-schema.json","watch":"watchify src/embed.js -v -d -s vg.embed -o vega-embed.js"},"browserify":{"transform":["browserify-shim"]},"browserify-shim":{"d3":"global:d3","vega":"global:vg"},"gitHead":"1340de15d82f3648b0d5c033370504bed0d4209c","bugs":{"url":"https://github.com/vega/vega-embed/issues"},"homepage":"https://github.com/vega/vega-embed#readme","_id":"vega-embed@1.0.9","_shasum":"29a29cc98ae5f97d68787a2c2bd6e26639d73f2e","_from":".","_npmVersion":"2.12.1","_nodeVersion":"0.12.7","_npmUser":{"name":"jheer","email":"jeffrey.heer@gmail.com"},"maintainers":[{"name":"jheer","email":"jeffrey.heer@gmail.com"}],"dist":{"shasum":"29a29cc98ae5f97d68787a2c2bd6e26639d73f2e","tarball":"https://registry.npmjs.org/vega-embed/-/vega-embed-1.0.9.tgz"},"directories":{}},"2.0.0":{"name":"vega-embed","version":"2.0.0","description":"Publish Vega visualizations as embedded web components.","keywords":["vega","data","visualization","component","embed"],"repository":{"type":"git","url":"git+ssh://git@github.com/vega/vega-embed.git"},"author":{"name":"Jeffrey Heer","url":"http://idl.cs.washington.edu"},"license":"BSD-3-Clause","devDependencies":{"d3":"^3.5.11","d3-geo-projection":"^0.2.15","topojson":"^1.6.19","vega":"^2.4.1","vega-lite":"^0.9.2","browserify":"^12.0.1","browserify-shim":"^3.8.11","chai":"^3.4.1","jshint":"^2.9.1-rc1","mocha":"^2.3.4","tv4":"^1.2.7","uglify-js":"^2.6.1"},"scripts":{"deploy":"npm run lint && npm run test && scripts/deploy.sh","lint":"jshint src/","test":"npm run schema && mocha --timeout 5000 --recursive test/","build":"browserify src/embed.js -d -s vg.embed > vega-embed.js","postbuild":"uglifyjs vega-embed.js -cm > vega-embed.min.js","schema":"node scripts/schema.js > vega-embed-schema.json","watch":"watchify src/embed.js -v -d -s vg.embed -o vega-embed.js"},"browserify":{"transform":["browserify-shim"]},"browserify-shim":{"d3":"global:d3","vega":"global:vg","vega-lite":"global:vl"},"gitHead":"9226e5873b6c94ef1b9390d816c53eb52da4823f","bugs":{"url":"https://github.com/vega/vega-embed/issues"},"homepage":"https://github.com/vega/vega-embed#readme","_id":"vega-embed@2.0.0","_shasum":"92ff5f63b869089699520d46c5e6969f4a333a98","_from":".","_npmVersion":"2.12.1","_nodeVersion":"0.12.7","_npmUser":{"name":"jheer","email":"jeffrey.heer@gmail.com"},"maintainers":[{"name":"jheer","email":"jeffrey.heer@gmail.com"}],"dist":{"shasum":"92ff5f63b869089699520d46c5e6969f4a333a98","tarball":"https://registry.npmjs.org/vega-embed/-/vega-embed-2.0.0.tgz"},"directories":{}},"2.1.0":{"name":"vega-embed","version":"2.1.0","description":"Publish Vega visualizations as embedded web components.","keywords":["vega","data","visualization","component","embed"],"repository":{"type":"git","url":"git+ssh://git@github.com/vega/vega-embed.git"},"author":{"name":"Jeffrey Heer","url":"http://idl.cs.washington.edu"},"license":"BSD-3-Clause","main":"src/embed.js","devDependencies":{"d3":"^3.5.16","d3-geo-projection":"^0.2.16","topojson":"^1.6.24","vega":"^2.5.0","vega-lite":"^1.0.7","browserify":"^13.0.0","browserify-shim":"^3.8.12","chai":"^3.5.0","jshint":"^2.9.1","mocha":"^2.4.5","tv4":"^1.2.7","uglify-js":"^2.6.2"},"scripts":{"deploy":"npm run lint && npm run test && scripts/deploy.sh","lint":"jshint src/","test":"npm run schema && mocha --timeout 5000 --recursive test/","build":"browserify src/embed.js -d -s vg.embed > vega-embed.js","postbuild":"uglifyjs vega-embed.js -cm > vega-embed.min.js","schema":"node scripts/schema.js > vega-embed-schema.json","watch":"watchify src/embed.js -v -d -s vg.embed -o vega-embed.js"},"browserify":{"transform":["browserify-shim"]},"browserify-shim":{"d3":"global:d3","vega":"global:vg","vega-lite":"global:vl"},"gitHead":"1009bb4a6e3aceeb3169321d5852657be2e05e84","bugs":{"url":"https://github.com/vega/vega-embed/issues"},"homepage":"https://github.com/vega/vega-embed#readme","_id":"vega-embed@2.1.0","_shasum":"d926dbb9086d36d6c1837773b564be694d9626d1","_from":".","_npmVersion":"2.12.1","_nodeVersion":"0.12.7","_npmUser":{"name":"jheer","email":"jeffrey.heer@gmail.com"},"maintainers":[{"name":"jheer","email":"jeffrey.heer@gmail.com"}],"dist":{"shasum":"d926dbb9086d36d6c1837773b564be694d9626d1","tarball":"https://registry.npmjs.org/vega-embed/-/vega-embed-2.1.0.tgz"},"_npmOperationalInternal":{"host":"packages-5-east.internal.npmjs.com","tmp":"tmp/vega-embed-2.1.0.tgz_1456850643623_0.7886923286132514"},"directories":{}},"2.2.0":{"name":"vega-embed","version":"2.2.0","description":"Publish Vega visualizations as embedded web components.","keywords":["vega","data","visualization","component","embed"],"repository":{"type":"git","url":"git+ssh://git@github.com/vega/vega-embed.git"},"author":{"name":"Jeffrey Heer","url":"http://idl.cs.washington.edu"},"contributors":[{"name":"Arvind Satyanarayan","url":"http://arvindsatya.com"}],"license":"BSD-3-Clause","main":"src/embed.js","devDependencies":{"browserify":"^13.0.0","browserify-shim":"^3.8.12","chai":"^3.5.0","d3":"^3.5.16","d3-geo-projection":"^0.2.16","jshint":"^2.9.1","mocha":"^2.4.5","topojson":"^1.6.24","tv4":"^1.2.7","uglify-js":"^2.6.2","vega":"^2.5.0","vega-lite":"^1.0.7","watchify":"^3.7.0"},"scripts":{"deploy":"npm run lint && npm run test && scripts/deploy.sh","lint":"jshint src/","test":"npm run schema && mocha --timeout 5000 --recursive test/","build":"browserify src/embed.js -d -s vg.embed > vega-embed.js","postbuild":"uglifyjs vega-embed.js -cm > vega-embed.min.js","schema":"node scripts/schema.js > vega-embed-schema.json","watch":"watchify src/embed.js -v -d -s vg.embed -o vega-embed.js"},"browserify":{"transform":["browserify-shim"]},"browserify-shim":{"d3":"global:d3","vega":"global:vg","vega-lite":"global:vl"},"gitHead":"2115d270a765599483d890d80603f436efea7525","bugs":{"url":"https://github.com/vega/vega-embed/issues"},"homepage":"https://github.com/vega/vega-embed#readme","_id":"vega-embed@2.2.0","_shasum":"b22fb70c5436dd20b55595a2c6c3321d35c4c9a4","_from":".","_npmVersion":"2.12.1","_nodeVersion":"0.12.7","_npmUser":{"name":"jheer","email":"jeffrey.heer@gmail.com"},"maintainers":[{"name":"jheer","email":"jeffrey.heer@gmail.com"}],"dist":{"shasum":"b22fb70c5436dd20b55595a2c6c3321d35c4c9a4","tarball":"https://registry.npmjs.org/vega-embed/-/vega-embed-2.2.0.tgz"},"_npmOperationalInternal":{"host":"packages-12-west.internal.npmjs.com","tmp":"tmp/vega-embed-2.2.0.tgz_1466532511088_0.37788703734986484"},"directories":{}},"3.0.0-beta.0":{"name":"vega-embed","version":"3.0.0-beta.0","description":"Publish Vega visualizations as embedded web components.","keywords":["vega","data","visualization","component","embed"],"repository":{"type":"git","url":"git+ssh://git@github.com/vega/vega-embed.git"},"author":{"name":"UW Interactive Data Lab","url":"http://idl.cs.washington.edu"},"contributors":[{"name":"Jeffrey Heer","url":"https://homes.cs.washington.edu/~jheer/"},{"name":"Arvind Satyanarayan","url":"http://arvindsatya.com"},{"name":"Younghoon Kim"},{"name":"Dominik Moritz","url":"https://www.domoritz.de"}],"license":"BSD-3-Clause","main":"src/embed.js","devDependencies":{"browserify":"^14.0.0","browserify-shim":"^3.8.13","eslint":"^3.14.1","uglify-js":"^2.7.5","vega":"3.0.0-beta.20","vega-lite":"2.0.0-alpha.1","d3-selection":"^1.0.3","watchify":"^3.9.0","vega-schema-url-parser":"^1.0.0-beta.2"},"scripts":{"deploy":"npm run lint && scripts/deploy.sh","lint":"eslint src/","build":"browserify src/embed.js -d -s vega.embed > vega-embed.js","postbuild":"uglifyjs vega-embed.js -cm > vega-embed.min.js","watch":"watchify src/embed.js -v -d -s vega.embed -o vega-embed.js"},"browserify":{"transform":["browserify-shim"]},"browserify-shim":{"vega":"global:vega","vega-lite":"global:vl"},"gitHead":"1e8738f284b73de4acf3e38d99f3616ecd498f8c","bugs":{"url":"https://github.com/vega/vega-embed/issues"},"homepage":"https://github.com/vega/vega-embed#readme","_id":"vega-embed@3.0.0-beta.0","_shasum":"e92d89ecd41d2062f3bbc93f8c922c0cb85d8ecf","_from":".","_npmVersion":"4.1.2","_nodeVersion":"7.5.0","_npmUser":{"name":"domoritz","email":"domoritz@gmail.com"},"maintainers":[{"name":"domoritz","email":"domoritz@gmail.com"},{"name":"jheer","email":"jeffrey.heer@gmail.com"}],"dist":{"shasum":"e92d89ecd41d2062f3bbc93f8c922c0cb85d8ecf","tarball":"https://registry.npmjs.org/vega-embed/-/vega-embed-3.0.0-beta.0.tgz"},"_npmOperationalInternal":{"host":"packages-12-west.internal.npmjs.com","tmp":"tmp/vega-embed-3.0.0-beta.0.tgz_1487002903548_0.944536613067612"},"directories":{}},"3.0.0-beta.1":{"name":"vega-embed","version":"3.0.0-beta.1","description":"Publish Vega visualizations as embedded web components.","keywords":["vega","data","visualization","component","embed"],"repository":{"type":"git","url":"git+ssh://git@github.com/vega/vega-embed.git"},"author":{"name":"UW Interactive Data Lab","url":"http://idl.cs.washington.edu"},"contributors":[{"name":"Jeffrey Heer","url":"https://homes.cs.washington.edu/~jheer/"},{"name":"Arvind Satyanarayan","url":"http://arvindsatya.com"},{"name":"Younghoon Kim"},{"name":"Dominik Moritz","url":"https://www.domoritz.de"}],"license":"BSD-3-Clause","main":"src/embed.js","devDependencies":{"browserify":"^14.1.0","browserify-shim":"^3.8.13","eslint":"^3.14.1","uglify-js":"^2.7.5","vega":"3.0.0-beta.22","vega-lite":"2.0.0-alpha.1","watchify":"^3.9.0"},"dependencies":{"d3-selection":"^1.0.3","vega-schema-url-parser":"^1.0.0-beta.2"},"peerDependencies":{"vega":"3","vega-lite":"2"},"scripts":{"deploy":"npm run lint && scripts/deploy.sh","lint":"eslint src/","build":"browserify src/embed.js -d -s vega.embed > vega-embed.js","postbuild":"uglifyjs vega-embed.js -cm > vega-embed.min.js","watch":"watchify src/embed.js -v -d -s vega.embed -o vega-embed.js"},"browserify":{"transform":["browserify-shim"]},"browserify-shim":{"vega":"global:vega","vega-lite":"global:vl"},"gitHead":"757f4c8e15e35677686ce62e6fe9c7a53c54f8e0","bugs":{"url":"https://github.com/vega/vega-embed/issues"},"homepage":"https://github.com/vega/vega-embed#readme","_id":"vega-embed@3.0.0-beta.1","_shasum":"9e174fbb528edb7cc00b0d67c4dbcf99e0f8d811","_from":".","_npmVersion":"4.1.2","_nodeVersion":"7.5.0","_npmUser":{"name":"domoritz","email":"domoritz@gmail.com"},"dist":{"shasum":"9e174fbb528edb7cc00b0d67c4dbcf99e0f8d811","tarball":"https://registry.npmjs.org/vega-embed/-/vega-embed-3.0.0-beta.1.tgz"},"maintainers":[{"name":"domoritz","email":"domoritz@gmail.com"},{"name":"jheer","email":"jeffrey.heer@gmail.com"}],"_npmOperationalInternal":{"host":"packages-12-west.internal.npmjs.com","tmp":"tmp/vega-embed-3.0.0-beta.1.tgz_1487267554567_0.9576026776339859"},"directories":{}},"3.0.0-beta.2":{"name":"vega-embed","version":"3.0.0-beta.2","description":"Publish Vega visualizations as embedded web components.","keywords":["vega","data","visualization","component","embed"],"repository":{"type":"git","url":"git+ssh://git@github.com/vega/vega-embed.git"},"author":{"name":"UW Interactive Data Lab","url":"http://idl.cs.washington.edu"},"contributors":[{"name":"Jeffrey Heer","url":"https://homes.cs.washington.edu/~jheer/"},{"name":"Arvind Satyanarayan","url":"http://arvindsatya.com"},{"name":"Younghoon Kim"},{"name":"Dominik Moritz","url":"https://www.domoritz.de"}],"license":"BSD-3-Clause","main":"src/embed.js","devDependencies":{"browserify":"^14.1.0","browserify-shim":"^3.8.13","eslint":"^3.14.1","uglify-js":"^2.7.5","vega":"3.0.0-beta.22","vega-lite":"2.0.0-alpha.1","watchify":"^3.9.0"},"dependencies":{"d3-selection":"^1.0.3","vega-schema-url-parser":"^1.0.0-beta.2"},"peerDependencies":{"vega":"3","vega-lite":"2"},"scripts":{"deploy":"npm run lint && scripts/deploy.sh","lint":"eslint src/","build":"browserify src/embed.js -d -s vega.embed > vega-embed.js","postbuild":"uglifyjs vega-embed.js -cm > vega-embed.min.js","watch":"watchify src/embed.js -v -d -s vega.embed -o vega-embed.js"},"browserify":{"transform":["browserify-shim"]},"browserify-shim":{"vega":"global:vega","vega-lite":"global:vl"},"gitHead":"12d9a9b065d4c234ad6fc7d0efb9cff94d941a57","bugs":{"url":"https://github.com/vega/vega-embed/issues"},"homepage":"https://github.com/vega/vega-embed#readme","_id":"vega-embed@3.0.0-beta.2","_shasum":"28782a97b7cf6d58f7fc088c037e8f4fd9ab0428","_from":".","_npmVersion":"4.3.0","_nodeVersion":"7.6.0","_npmUser":{"name":"domoritz","email":"domoritz@gmail.com"},"dist":{"shasum":"28782a97b7cf6d58f7fc088c037e8f4fd9ab0428","tarball":"https://registry.npmjs.org/vega-embed/-/vega-embed-3.0.0-beta.2.tgz"},"maintainers":[{"name":"domoritz","email":"domoritz@gmail.com"},{"name":"jheer","email":"jeffrey.heer@gmail.com"}],"_npmOperationalInternal":{"host":"packages-18-east.internal.npmjs.com","tmp":"tmp/vega-embed-3.0.0-beta.2.tgz_1488070189775_0.9886077654082328"},"directories":{}},"3.0.0-beta.3":{"name":"vega-embed","version":"3.0.0-beta.3","description":"Publish Vega visualizations as embedded web components.","keywords":["vega","data","visualization","component","embed"],"repository":{"type":"git","url":"git+ssh://git@github.com/vega/vega-embed.git"},"author":{"name":"UW Interactive Data Lab","url":"http://idl.cs.washington.edu"},"contributors":[{"name":"Jeffrey Heer","url":"https://homes.cs.washington.edu/~jheer/"},{"name":"Arvind Satyanarayan","url":"http://arvindsatya.com"},{"name":"Younghoon Kim"},{"name":"Dominik Moritz","url":"https://www.domoritz.de"}],"license":"BSD-3-Clause","main":"src/embed.js","devDependencies":{"browserify":"^14.1.0","browserify-shim":"^3.8.13","eslint":"^3.14.1","uglify-js":"^2.7.5","vega":"3.0.0-beta.22","vega-lite":"2.0.0-alpha.2","watchify":"^3.9.0"},"dependencies":{"d3-selection":"^1.0.3","vega-schema-url-parser":"^1.0.0-beta.2"},"peerDependencies":{"vega":">3.0.0-beta","vega-lite":">2.0.0-alpha"},"scripts":{"deploy":"npm run lint && scripts/deploy.sh","lint":"eslint src/","build":"browserify src/embed.js -d -s vega.embed > vega-embed.js","postbuild":"uglifyjs vega-embed.js -cm > vega-embed.min.js","watch":"watchify src/embed.js -v -d -s vega.embed -o vega-embed.js"},"browserify":{"transform":["browserify-shim"]},"browserify-shim":{"vega":"global:vega","vega-lite":"global:vl"},"gitHead":"648ff6cd38bebb7352e1153a5db082a6215ddab0","bugs":{"url":"https://github.com/vega/vega-embed/issues"},"homepage":"https://github.com/vega/vega-embed#readme","_id":"vega-embed@3.0.0-beta.3","_shasum":"3aa276ae166fec35b8ed2c5911d35f383739149a","_from":".","_npmVersion":"4.3.0","_nodeVersion":"7.6.0","_npmUser":{"name":"domoritz","email":"domoritz@gmail.com"},"dist":{"shasum":"3aa276ae166fec35b8ed2c5911d35f383739149a","tarball":"https://registry.npmjs.org/vega-embed/-/vega-embed-3.0.0-beta.3.tgz"},"maintainers":[{"name":"domoritz","email":"domoritz@gmail.com"},{"name":"jheer","email":"jeffrey.heer@gmail.com"}],"_npmOperationalInternal":{"host":"packages-12-west.internal.npmjs.com","tmp":"tmp/vega-embed-3.0.0-beta.3.tgz_1488070855211_0.19531172537244856"},"directories":{}},"3.0.0-beta.4":{"name":"vega-embed","version":"3.0.0-beta.4","description":"Publish Vega visualizations as embedded web components.","keywords":["vega","data","visualization","component","embed"],"repository":{"type":"git","url":"git+ssh://git@github.com/vega/vega-embed.git"},"author":{"name":"UW Interactive Data Lab","url":"http://idl.cs.washington.edu"},"contributors":[{"name":"Jeffrey Heer","url":"https://homes.cs.washington.edu/~jheer/"},{"name":"Arvind Satyanarayan","url":"http://arvindsatya.com"},{"name":"Younghoon Kim"},{"name":"Dominik Moritz","url":"https://www.domoritz.de"}],"license":"BSD-3-Clause","main":"src/embed.js","devDependencies":{"browserify":"^14.1.0","browserify-shim":"^3.8.13","eslint":"^3.14.1","uglify-js":"^2.7.5","vega":"3.0.0-beta.22","vega-lite":"2.0.0-alpha.2","watchify":"^3.9.0"},"dependencies":{"d3-selection":"^1.0.3","vega-schema-url-parser":"^1.0.0-beta.2"},"peerDependencies":{"vega":">3.0.0-beta","vega-lite":">2.0.0-alpha"},"scripts":{"deploy":"npm run lint && scripts/deploy.sh","lint":"eslint src/","build":"browserify src/embed.js -d -s vega.embed > vega-embed.js","postbuild":"uglifyjs vega-embed.js -cm > vega-embed.min.js","watch":"watchify src/embed.js -v -d -s vega.embed -o vega-embed.js"},"browserify":{"transform":["browserify-shim"]},"browserify-shim":{"vega":"global:vega","vega-lite":"global:vl"},"gitHead":"31292466d0e209b7e39dc905bb5ececa11345294","bugs":{"url":"https://github.com/vega/vega-embed/issues"},"homepage":"https://github.com/vega/vega-embed#readme","_id":"vega-embed@3.0.0-beta.4","_shasum":"8b7eee137db0b1cb20f61a64ff4f48d44db98fdb","_from":".","_npmVersion":"4.3.0","_nodeVersion":"7.6.0","_npmUser":{"name":"domoritz","email":"domoritz@gmail.com"},"dist":{"shasum":"8b7eee137db0b1cb20f61a64ff4f48d44db98fdb","tarball":"https://registry.npmjs.org/vega-embed/-/vega-embed-3.0.0-beta.4.tgz"},"maintainers":[{"name":"domoritz","email":"domoritz@gmail.com"},{"name":"jheer","email":"jeffrey.heer@gmail.com"}],"_npmOperationalInternal":{"host":"packages-18-east.internal.npmjs.com","tmp":"tmp/vega-embed-3.0.0-beta.4.tgz_1488071140454_0.6681433373596519"},"directories":{}},"3.0.0-beta.5":{"name":"vega-embed","version":"3.0.0-beta.5","description":"Publish Vega visualizations as embedded web components.","keywords":["vega","data","visualization","component","embed"],"repository":{"type":"git","url":"git+ssh://git@github.com/vega/vega-embed.git"},"author":{"name":"UW Interactive Data Lab","url":"http://idl.cs.washington.edu"},"contributors":[{"name":"Jeffrey Heer","url":"https://homes.cs.washington.edu/~jheer/"},{"name":"Arvind Satyanarayan","url":"http://arvindsatya.com"},{"name":"Younghoon Kim"},{"name":"Dominik Moritz","url":"https://www.domoritz.de"}],"license":"BSD-3-Clause","main":"src/embed.js","devDependencies":{"browserify":"^14.1.0","browserify-shim":"^3.8.13","eslint":"^3.16.1","uglify-js":"^2.8.4","watchify":"^3.9.0"},"dependencies":{"d3-selection":"^1.0.4","vega-schema-url-parser":"^1.0.0-beta.2","vega":"^3.0.0-beta.25","vega-lite":"^2.0.0-alpha.4"},"scripts":{"deploy":"npm run lint && scripts/deploy.sh","lint":"eslint src/","build":"browserify src/embed.js -d -s vega.embed > vega-embed.js","postbuild":"uglifyjs vega-embed.js -cm > vega-embed.min.js","watch":"watchify src/embed.js -v -d -s vega.embed -o vega-embed.js"},"browserify":{"transform":["browserify-shim"]},"browserify-shim":{"vega":"global:vega","vega-lite":"global:vl"},"gitHead":"40a1133d3f38c17ba8b13c6d9edad26696868f8f","bugs":{"url":"https://github.com/vega/vega-embed/issues"},"homepage":"https://github.com/vega/vega-embed#readme","_id":"vega-embed@3.0.0-beta.5","_shasum":"4fe3a77d78f96de88ef12018734a1dccccc808d0","_from":".","_npmVersion":"4.3.0","_nodeVersion":"7.6.0","_npmUser":{"name":"domoritz","email":"domoritz@gmail.com"},"dist":{"shasum":"4fe3a77d78f96de88ef12018734a1dccccc808d0","tarball":"https://registry.npmjs.org/vega-embed/-/vega-embed-3.0.0-beta.5.tgz"},"maintainers":[{"name":"domoritz","email":"domoritz@gmail.com"},{"name":"jheer","email":"jeffrey.heer@gmail.com"}],"_npmOperationalInternal":{"host":"packages-12-west.internal.npmjs.com","tmp":"tmp/vega-embed-3.0.0-beta.5.tgz_1488415083273_0.6511702784337103"},"directories":{}},"3.0.0-beta.6":{"name":"vega-embed","version":"3.0.0-beta.6","description":"Publish Vega visualizations as embedded web components.","keywords":["vega","data","visualization","component","embed"],"repository":{"type":"git","url":"git+ssh://git@github.com/vega/vega-embed.git"},"author":{"name":"UW Interactive Data Lab","url":"http://idl.cs.washington.edu"},"contributors":[{"name":"Jeffrey Heer","url":"https://homes.cs.washington.edu/~jheer/"},{"name":"Arvind Satyanarayan","url":"http://arvindsatya.com"},{"name":"Younghoon Kim"},{"name":"Dominik Moritz","url":"https://www.domoritz.de"}],"license":"BSD-3-Clause","main":"src/embed.js","devDependencies":{"browserify":"^14.1.0","browserify-shim":"^3.8.13","eslint":"^3.16.1","uglify-js":"^2.8.4","watchify":"^3.9.0","vega":"^3.0.0-beta.25","vega-lite":"^2.0.0-alpha.4"},"dependencies":{"d3-selection":"^1.0.4","vega-schema-url-parser":"^1.0.0-beta.2"},"scripts":{"deploy":"npm run lint && scripts/deploy.sh","lint":"eslint src/","build":"browserify src/embed.js -d -s vega.embed > vega-embed.js","postbuild":"uglifyjs vega-embed.js -cm > vega-embed.min.js","watch":"watchify src/embed.js -v -d -s vega.embed -o vega-embed.js"},"browserify":{"transform":["browserify-shim"]},"browserify-shim":{"vega":"global:vega","vega-lite":"global:vl"},"gitHead":"0ecd12eaa23868a1d062ff989d45c437397caa2d","bugs":{"url":"https://github.com/vega/vega-embed/issues"},"homepage":"https://github.com/vega/vega-embed#readme","_id":"vega-embed@3.0.0-beta.6","_shasum":"cfcabf3c04454fc093884e03e6373cea15b3bebb","_from":".","_npmVersion":"4.4.1","_nodeVersion":"7.7.2","_npmUser":{"name":"domoritz","email":"domoritz@gmail.com"},"dist":{"shasum":"cfcabf3c04454fc093884e03e6373cea15b3bebb","tarball":"https://registry.npmjs.org/vega-embed/-/vega-embed-3.0.0-beta.6.tgz"},"maintainers":[{"name":"domoritz","email":"domoritz@gmail.com"},{"name":"jheer","email":"jeffrey.heer@gmail.com"}],"_npmOperationalInternal":{"host":"packages-18-east.internal.npmjs.com","tmp":"tmp/vega-embed-3.0.0-beta.6.tgz_1489184426343_0.8093812097795308"},"directories":{}},"3.0.0-beta.7":{"name":"vega-embed","version":"3.0.0-beta.7","description":"Publish Vega visualizations as embedded web components.","keywords":["vega","data","visualization","component","embed"],"repository":{"type":"git","url":"git+ssh://git@github.com/vega/vega-embed.git"},"author":{"name":"UW Interactive Data Lab","url":"http://idl.cs.washington.edu"},"contributors":[{"name":"Jeffrey Heer","url":"https://homes.cs.washington.edu/~jheer/"},{"name":"Arvind Satyanarayan","url":"http://arvindsatya.com"},{"name":"Younghoon Kim"},{"name":"Dominik Moritz","url":"https://www.domoritz.de"}],"license":"BSD-3-Clause","main":"src/embed.js","devDependencies":{"browserify":"^14.1.0","browserify-shim":"^3.8.13","eslint":"^3.17.1","uglify-js":"^2.8.11","watchify":"^3.9.0","vega":"^3.0.0-beta.25","vega-lite":"^2.0.0-alpha.4"},"dependencies":{"d3-selection":"^1.0.5","vega-schema-url-parser":"^1.0.0-beta.2"},"scripts":{"deploy":"npm run lint && scripts/deploy.sh","lint":"eslint src/","build":"browserify src/embed.js -t browserify-shim -d -s vega.embed > vega-embed.js","postbuild":"uglifyjs vega-embed.js -cm > vega-embed.min.js","watch":"watchify src/embed.js -t browserify-shim -v -d -s vega.embed -o vega-embed.js"},"browserify-shim":{"vega":"global:vega","vega-lite":"global:vl"},"gitHead":"c164dd2a8c18a94d2a2382262ad369f44ea4954d","bugs":{"url":"https://github.com/vega/vega-embed/issues"},"homepage":"https://github.com/vega/vega-embed#readme","_id":"vega-embed@3.0.0-beta.7","_shasum":"f36cce00368110e8febbb2056612e16755c6b266","_from":".","_npmVersion":"4.4.4","_nodeVersion":"7.7.4","_npmUser":{"name":"domoritz","email":"domoritz@gmail.com"},"dist":{"shasum":"f36cce00368110e8febbb2056612e16755c6b266","tarball":"https://registry.npmjs.org/vega-embed/-/vega-embed-3.0.0-beta.7.tgz"},"maintainers":[{"name":"domoritz","email":"domoritz@gmail.com"},{"name":"jheer","email":"jeffrey.heer@gmail.com"}],"_npmOperationalInternal":{"host":"packages-12-west.internal.npmjs.com","tmp":"tmp/vega-embed-3.0.0-beta.7.tgz_1490726350589_0.7057664217427373"},"directories":{}},"3.0.0-beta.8":{"name":"vega-embed","version":"3.0.0-beta.8","description":"Publish Vega visualizations as embedded web components.","keywords":["vega","data","visualization","component","embed"],"repository":{"type":"git","url":"git+ssh://git@github.com/vega/vega-embed.git"},"author":{"name":"UW Interactive Data Lab","url":"http://idl.cs.washington.edu"},"contributors":[{"name":"Jeffrey Heer","url":"https://homes.cs.washington.edu/~jheer/"},{"name":"Arvind Satyanarayan","url":"http://arvindsatya.com"},{"name":"Younghoon Kim"},{"name":"Dominik Moritz","url":"https://www.domoritz.de"}],"license":"BSD-3-Clause","main":"src/embed.js","devDependencies":{"browserify":"^14.3.0","browserify-shim":"^3.8.14","eslint":"^3.19.0","uglify-js":"^2.8.22","watchify":"^3.9.0","vega":"^3.0.0-beta.28","vega-lite":"^2.0.0-alpha.8"},"dependencies":{"d3-selection":"^1.0.5","vega-schema-url-parser":"^1.0.0-beta.2"},"scripts":{"deploy":"npm run lint && scripts/deploy.sh","lint":"eslint src/","build":"browserify src/embed.js -t browserify-shim -d -s vega.embed > vega-embed.js","postbuild":"uglifyjs vega-embed.js -cm > vega-embed.min.js","watch":"watchify src/embed.js -t browserify-shim -v -d -s vega.embed -o vega-embed.js"},"browserify-shim":{"vega":"global:vega","vega-lite":"global:vl"},"gitHead":"1cd299f076f70252d1254378fd4014154dccffc2","bugs":{"url":"https://github.com/vega/vega-embed/issues"},"homepage":"https://github.com/vega/vega-embed#readme","_id":"vega-embed@3.0.0-beta.8","_shasum":"dcf736baf93d65a8d843b633fed6b34f11c53dc8","_from":".","_npmVersion":"4.5.0","_nodeVersion":"7.8.0","_npmUser":{"name":"domoritz","email":"domoritz@gmail.com"},"dist":{"shasum":"dcf736baf93d65a8d843b633fed6b34f11c53dc8","tarball":"https://registry.npmjs.org/vega-embed/-/vega-embed-3.0.0-beta.8.tgz"},"maintainers":[{"name":"domoritz","email":"domoritz@gmail.com"},{"name":"jheer","email":"jeffrey.heer@gmail.com"}],"_npmOperationalInternal":{"host":"packages-12-west.internal.npmjs.com","tmp":"tmp/vega-embed-3.0.0-beta.8.tgz_1491873956418_0.25026347138918936"},"directories":{}},"3.0.0-beta.9":{"name":"vega-embed","version":"3.0.0-beta.9","description":"Publish Vega visualizations as embedded web components.","keywords":["vega","data","visualization","component","embed"],"repository":{"type":"git","url":"git+ssh://git@github.com/vega/vega-embed.git"},"author":{"name":"UW Interactive Data Lab","url":"http://idl.cs.washington.edu"},"contributors":[{"name":"Jeffrey Heer","url":"https://homes.cs.washington.edu/~jheer/"},{"name":"Arvind Satyanarayan","url":"http://arvindsatya.com"},{"name":"Younghoon Kim"},{"name":"Dominik Moritz","url":"https://www.domoritz.de"}],"license":"BSD-3-Clause","main":"src/embed.js","devDependencies":{"browserify":"^14.3.0","browserify-shim":"^3.8.14","eslint":"^3.19.0","uglify-js":"^2.8.22","watchify":"^3.9.0"},"dependencies":{"vega":"^3.0.0-beta.28","vega-lite":"^2.0.0-alpha.8","d3-selection":"^1.0.5","vega-schema-url-parser":"^1.0.0-beta.2"},"scripts":{"deploy":"npm run lint && scripts/deploy.sh","lint":"eslint src/","build":"browserify src/embed.js -t browserify-shim -d -s vega.embed > vega-embed.js","postbuild":"uglifyjs vega-embed.js -cm > vega-embed.min.js","watch":"watchify src/embed.js -t browserify-shim -v -d -s vega.embed -o vega-embed.js"},"browserify-shim":{"vega":"global:vega","vega-lite":"global:vl"},"gitHead":"e4d902f2ecaad46f6f964b0e2753dd84c644574a","bugs":{"url":"https://github.com/vega/vega-embed/issues"},"homepage":"https://github.com/vega/vega-embed#readme","_id":"vega-embed@3.0.0-beta.9","_shasum":"18a17a1a85ba99ad1f672b488871a8f38ca630a7","_from":".","_npmVersion":"4.5.0","_nodeVersion":"7.8.0","_npmUser":{"name":"domoritz","email":"domoritz@gmail.com"},"dist":{"shasum":"18a17a1a85ba99ad1f672b488871a8f38ca630a7","tarball":"https://registry.npmjs.org/vega-embed/-/vega-embed-3.0.0-beta.9.tgz"},"maintainers":[{"name":"domoritz","email":"domoritz@gmail.com"},{"name":"jheer","email":"jeffrey.heer@gmail.com"}],"_npmOperationalInternal":{"host":"packages-18-east.internal.npmjs.com","tmp":"tmp/vega-embed-3.0.0-beta.9.tgz_1491874780878_0.4508601000998169"},"directories":{}},"3.0.0-beta.10":{"name":"vega-embed","version":"3.0.0-beta.10","description":"Publish Vega visualizations as embedded web components.","keywords":["vega","data","visualization","component","embed"],"repository":{"type":"git","url":"git+ssh://git@github.com/vega/vega-embed.git"},"author":{"name":"UW Interactive Data Lab","url":"http://idl.cs.washington.edu"},"contributors":[{"name":"Jeffrey Heer","url":"https://homes.cs.washington.edu/~jheer/"},{"name":"Arvind Satyanarayan","url":"http://arvindsatya.com"},{"name":"Younghoon Kim"},{"name":"Dominik Moritz","url":"https://www.domoritz.de"}],"license":"BSD-3-Clause","main":"src/embed.js","devDependencies":{"browserify":"^14.3.0","browserify-shim":"^3.8.14","eslint":"^3.19.0","uglify-js":"^2.8.22","watchify":"^3.9.0"},"dependencies":{"vega":"^3.0.0-beta.28","vega-lite":"^2.0.0-alpha.8","d3-selection":"^1.0.5","vega-schema-url-parser":"^1.0.0-beta.2"},"scripts":{"deploy":"npm run lint && scripts/deploy.sh","lint":"eslint src/","build":"browserify src/embed.js -t browserify-shim -d -s vega.embed > vega-embed.js","postbuild":"uglifyjs vega-embed.js -cm > vega-embed.min.js","watch":"watchify src/embed.js -t browserify-shim -v -d -s vega.embed -o vega-embed.js"},"browserify-shim":{"vega":"global:vega","vega-lite":"global:vl"},"gitHead":"0f0c81be8c5eea513bf3fad06550c469eaa891bc","bugs":{"url":"https://github.com/vega/vega-embed/issues"},"homepage":"https://github.com/vega/vega-embed#readme","_id":"vega-embed@3.0.0-beta.10","_shasum":"3f7d8c01a8bd8eab00cbc937edc6c6b6bf6e3d3e","_from":".","_npmVersion":"4.5.0","_nodeVersion":"7.8.0","_npmUser":{"name":"domoritz","email":"domoritz@gmail.com"},"dist":{"shasum":"3f7d8c01a8bd8eab00cbc937edc6c6b6bf6e3d3e","tarball":"https://registry.npmjs.org/vega-embed/-/vega-embed-3.0.0-beta.10.tgz"},"maintainers":[{"name":"domoritz","email":"domoritz@gmail.com"},{"name":"jheer","email":"jeffrey.heer@gmail.com"}],"_npmOperationalInternal":{"host":"packages-12-west.internal.npmjs.com","tmp":"tmp/vega-embed-3.0.0-beta.10.tgz_1492129254141_0.41519853193312883"},"directories":{}},"3.0.0-beta.11":{"name":"vega-embed","version":"3.0.0-beta.11","description":"Publish Vega visualizations as embedded web components.","keywords":["vega","data","visualization","component","embed"],"repository":{"type":"git","url":"git+ssh://git@github.com/vega/vega-embed.git"},"author":{"name":"UW Interactive Data Lab","url":"http://idl.cs.washington.edu"},"contributors":[{"name":"Jeffrey Heer","url":"https://homes.cs.washington.edu/~jheer/"},{"name":"Arvind Satyanarayan","url":"http://arvindsatya.com"},{"name":"Younghoon Kim"},{"name":"Dominik Moritz","url":"https://www.domoritz.de"}],"license":"BSD-3-Clause","main":"src/embed.js","devDependencies":{"browserify":"^14.3.0","browserify-shim":"^3.8.14","eslint":"^3.19.0","uglify-js":"^2.8.22","watchify":"^3.9.0"},"dependencies":{"vega":"^3.0.0-beta.30","vega-lite":"^2.0.0-beta.1","d3-selection":"^1.0.5","vega-schema-url-parser":"^1.0.0-beta.2"},"scripts":{"deploy":"npm run lint && scripts/deploy.sh","lint":"eslint src/","build":"browserify src/embed.js -t browserify-shim -d -s vega.embed > vega-embed.js","postbuild":"uglifyjs vega-embed.js -cm > vega-embed.min.js","watch":"watchify src/embed.js -t browserify-shim -v -d -s vega.embed -o vega-embed.js"},"browserify-shim":{"vega":"global:vega","vega-lite":"global:vl"},"gitHead":"0575712a45a9469e2945f5b1c9ea65db6f9dba3d","bugs":{"url":"https://github.com/vega/vega-embed/issues"},"homepage":"https://github.com/vega/vega-embed#readme","_id":"vega-embed@3.0.0-beta.11","_shasum":"d9efb9920af9caa6c95107d75d07bab58b5e09f8","_from":".","_npmVersion":"4.5.0","_nodeVersion":"7.9.0","_npmUser":{"name":"domoritz","email":"domoritz@gmail.com"},"dist":{"shasum":"d9efb9920af9caa6c95107d75d07bab58b5e09f8","tarball":"https://registry.npmjs.org/vega-embed/-/vega-embed-3.0.0-beta.11.tgz"},"maintainers":[{"name":"domoritz","email":"domoritz@gmail.com"},{"name":"jheer","email":"jeffrey.heer@gmail.com"}],"_npmOperationalInternal":{"host":"packages-12-west.internal.npmjs.com","tmp":"tmp/vega-embed-3.0.0-beta.11.tgz_1493086003640_0.3679989278316498"},"directories":{}},"3.0.0-beta.12":{"name":"vega-embed","version":"3.0.0-beta.12","description":"Publish Vega visualizations as embedded web components.","keywords":["vega","data","visualization","component","embed"],"repository":{"type":"git","url":"git+ssh://git@github.com/vega/vega-embed.git"},"author":{"name":"UW Interactive Data Lab","url":"http://idl.cs.washington.edu"},"contributors":[{"name":"Jeffrey Heer","url":"https://homes.cs.washington.edu/~jheer/"},{"name":"Arvind Satyanarayan","url":"http://arvindsatya.com"},{"name":"Younghoon Kim"},{"name":"Dominik Moritz","url":"https://www.domoritz.de"}],"license":"BSD-3-Clause","main":"src/embed.js","devDependencies":{"browserify":"^14.3.0","browserify-shim":"^3.8.14","eslint":"^3.19.0","uglify-js":"^2.8.22","watchify":"^3.9.0"},"dependencies":{"vega":"^3.0.0-beta.30","vega-lite":"^2.0.0-beta.1","d3-selection":"^1.0.5","vega-schema-url-parser":"^1.0.0-beta.2"},"scripts":{"deploy":"npm run lint && scripts/deploy.sh","lint":"eslint src/","build":"browserify src/embed.js -t browserify-shim -d -s vega.embed > vega-embed.js","postbuild":"uglifyjs vega-embed.js -cm > vega-embed.min.js","watch":"watchify src/embed.js -t browserify-shim -v -d -s vega.embed -o vega-embed.js"},"browserify-shim":{"vega":"global:vega","vega-lite":"global:vl"},"gitHead":"73ae705fdbdec1d03fe1bb648d050ae61a616ad4","bugs":{"url":"https://github.com/vega/vega-embed/issues"},"homepage":"https://github.com/vega/vega-embed#readme","_id":"vega-embed@3.0.0-beta.12","_shasum":"cdaa9e0c68dacf6b88dfb279fc74b201e1b5a6a9","_from":".","_npmVersion":"4.5.0","_nodeVersion":"7.9.0","_npmUser":{"name":"domoritz","email":"domoritz@gmail.com"},"dist":{"shasum":"cdaa9e0c68dacf6b88dfb279fc74b201e1b5a6a9","tarball":"https://registry.npmjs.org/vega-embed/-/vega-embed-3.0.0-beta.12.tgz"},"maintainers":[{"name":"domoritz","email":"domoritz@gmail.com"},{"name":"jheer","email":"jeffrey.heer@gmail.com"}],"_npmOperationalInternal":{"host":"packages-18-east.internal.npmjs.com","tmp":"tmp/vega-embed-3.0.0-beta.12.tgz_1493577171128_0.03041056776419282"},"directories":{}},"3.0.0-beta.13":{"name":"vega-embed","version":"3.0.0-beta.13","description":"Publish Vega visualizations as embedded web components.","keywords":["vega","data","visualization","component","embed"],"repository":{"type":"git","url":"git+ssh://git@github.com/vega/vega-embed.git"},"author":{"name":"UW Interactive Data Lab","url":"http://idl.cs.washington.edu"},"contributors":[{"name":"Jeffrey Heer","url":"https://homes.cs.washington.edu/~jheer/"},{"name":"Arvind Satyanarayan","url":"http://arvindsatya.com"},{"name":"Younghoon Kim"},{"name":"Dominik Moritz","url":"https://www.domoritz.de"}],"license":"BSD-3-Clause","main":"src/embed.js","devDependencies":{"browserify":"^14.3.0","browserify-shim":"^3.8.14","eslint":"^3.19.0","uglify-js":"^2.8.22","watchify":"^3.9.0"},"dependencies":{"vega":"^3.0.0-beta.30","vega-lite":"^2.0.0-beta.2","d3-selection":"^1.0.5","vega-schema-url-parser":"^1.0.0-beta.2"},"scripts":{"deploy":"npm run lint && scripts/deploy.sh","lint":"eslint src/","build":"browserify src/embed.js -t browserify-shim -d -s vega.embed > vega-embed.js","postbuild":"uglifyjs vega-embed.js -cm > vega-embed.min.js","watch":"watchify src/embed.js -t browserify-shim -v -d -s vega.embed -o vega-embed.js"},"browserify-shim":{"vega":"global:vega","vega-lite":"global:vl"},"gitHead":"873d365eeaaf68110cf0601c4bd9d55984e76977","bugs":{"url":"https://github.com/vega/vega-embed/issues"},"homepage":"https://github.com/vega/vega-embed#readme","_id":"vega-embed@3.0.0-beta.13","_shasum":"b90a6b46f2422b8ccdc8d82e8d8685137ac6ccdd","_from":".","_npmVersion":"4.5.0","_nodeVersion":"7.9.0","_npmUser":{"name":"domoritz","email":"domoritz@gmail.com"},"dist":{"shasum":"b90a6b46f2422b8ccdc8d82e8d8685137ac6ccdd","tarball":"https://registry.npmjs.org/vega-embed/-/vega-embed-3.0.0-beta.13.tgz"},"maintainers":[{"name":"domoritz","email":"domoritz@gmail.com"},{"name":"jheer","email":"jeffrey.heer@gmail.com"}],"_npmOperationalInternal":{"host":"packages-12-west.internal.npmjs.com","tmp":"tmp/vega-embed-3.0.0-beta.13.tgz_1493577549598_0.5558832965325564"},"directories":{}},"3.0.0-beta.14":{"name":"vega-embed","version":"3.0.0-beta.14","description":"Publish Vega visualizations as embedded web components.","keywords":["vega","data","visualization","component","embed"],"repository":{"type":"git","url":"git+ssh://git@github.com/vega/vega-embed.git"},"author":{"name":"UW Interactive Data Lab","url":"http://idl.cs.washington.edu"},"contributors":[{"name":"Jeffrey Heer","url":"https://homes.cs.washington.edu/~jheer/"},{"name":"Arvind Satyanarayan","url":"http://arvindsatya.com"},{"name":"Younghoon Kim"},{"name":"Dominik Moritz","url":"https://www.domoritz.de"}],"license":"BSD-3-Clause","main":"src/embed.js","devDependencies":{"browserify":"^14.3.0","browserify-shim":"^3.8.14","eslint":"^3.19.0","uglify-js":"^2.8.22","watchify":"^3.9.0"},"dependencies":{"vega":"^3.0.0-beta.30","vega-lite":"^2.0.0-beta.1","d3-selection":"^1.0.5","vega-schema-url-parser":"^1.0.0-beta.2"},"scripts":{"deploy":"npm run lint && scripts/deploy.sh","lint":"eslint src/","build":"browserify src/embed.js -t browserify-shim -d -s vega.embed > vega-embed.js","postbuild":"uglifyjs vega-embed.js -cm > vega-embed.min.js","watch":"watchify src/embed.js -t browserify-shim -v -d -s vega.embed -o vega-embed.js"},"browserify-shim":{"vega":"global:vega","vega-lite":"global:vl"},"gitHead":"5cb807f580b2ce2dc4627853b0c097964ce67461","bugs":{"url":"https://github.com/vega/vega-embed/issues"},"homepage":"https://github.com/vega/vega-embed#readme","_id":"vega-embed@3.0.0-beta.14","_shasum":"9781130ab8fc91e3f76f33492807f6652f53d4ba","_from":".","_npmVersion":"4.5.0","_nodeVersion":"7.9.0","_npmUser":{"name":"domoritz","email":"domoritz@gmail.com"},"dist":{"shasum":"9781130ab8fc91e3f76f33492807f6652f53d4ba","tarball":"https://registry.npmjs.org/vega-embed/-/vega-embed-3.0.0-beta.14.tgz"},"maintainers":[{"name":"domoritz","email":"domoritz@gmail.com"},{"name":"jheer","email":"jeffrey.heer@gmail.com"}],"_npmOperationalInternal":{"host":"packages-12-west.internal.npmjs.com","tmp":"tmp/vega-embed-3.0.0-beta.14.tgz_1493577968798_0.8625354398973286"},"directories":{}},"3.0.0-beta.15":{"name":"vega-embed","version":"3.0.0-beta.15","description":"Publish Vega visualizations as embedded web components.","keywords":["vega","data","visualization","component","embed"],"repository":{"type":"git","url":"git+ssh://git@github.com/vega/vega-embed.git"},"author":{"name":"UW Interactive Data Lab","url":"http://idl.cs.washington.edu"},"contributors":[{"name":"Jeffrey Heer","url":"https://homes.cs.washington.edu/~jheer/"},{"name":"Arvind Satyanarayan","url":"http://arvindsatya.com"},{"name":"Younghoon Kim"},{"name":"Dominik Moritz","url":"https://www.domoritz.de"}],"license":"BSD-3-Clause","main":"src/embed.js","devDependencies":{"browserify":"^14.4.0","browserify-shim":"^3.8.14","eslint":"^3.19.0","uglify-js":"^3.0.13","watchify":"^3.9.0"},"dependencies":{"vega":"^3.0.0-beta.32","vega-lite":"^2.0.0-beta.3","d3-selection":"^1.1.0","vega-schema-url-parser":"^1.0.0-beta.2"},"scripts":{"deploy":"npm run lint && scripts/deploy.sh","lint":"eslint src/","build":"browserify src/embed.js -t browserify-shim -d -s vega.embed > vega-embed.js","postbuild":"uglifyjs vega-embed.js -cm > vega-embed.min.js","watch":"watchify src/embed.js -t browserify-shim -v -d -s vega.embed -o vega-embed.js"},"browserify-shim":{"vega":"global:vega","vega-lite":"global:vl"},"gitHead":"50945d08f2f6b669a9875152f42cf7d746c1f8c5","bugs":{"url":"https://github.com/vega/vega-embed/issues"},"homepage":"https://github.com/vega/vega-embed#readme","_id":"vega-embed@3.0.0-beta.15","_shasum":"90bbd394c6c381520216b0d228a5f652a90142a4","_from":".","_npmVersion":"4.6.1","_nodeVersion":"7.10.0","_npmUser":{"name":"domoritz","email":"domoritz@gmail.com"},"dist":{"shasum":"90bbd394c6c381520216b0d228a5f652a90142a4","tarball":"https://registry.npmjs.org/vega-embed/-/vega-embed-3.0.0-beta.15.tgz"},"maintainers":[{"name":"domoritz","email":"domoritz@gmail.com"},{"name":"jheer","email":"jeffrey.heer@gmail.com"}],"_npmOperationalInternal":{"host":"s3://npm-registry-packages","tmp":"tmp/vega-embed-3.0.0-beta.15.tgz_1496178177756_0.9925015582703054"},"directories":{}},"3.0.0-beta.16":{"name":"vega-embed","version":"3.0.0-beta.16","description":"Publish Vega visualizations as embedded web components.","keywords":["vega","data","visualization","component","embed"],"repository":{"type":"git","url":"git+ssh://git@github.com/vega/vega-embed.git"},"author":{"name":"UW Interactive Data Lab","url":"http://idl.cs.washington.edu"},"contributors":[{"name":"Jeffrey Heer","url":"https://homes.cs.washington.edu/~jheer/"},{"name":"Arvind Satyanarayan","url":"http://arvindsatya.com"},{"name":"Younghoon Kim"},{"name":"Dominik Moritz","url":"https://www.domoritz.de"}],"license":"BSD-3-Clause","main":"src/embed.js","devDependencies":{"browserify":"^14.4.0","browserify-shim":"^3.8.14","eslint":"^3.19.0","uglify-js":"^3.0.13","watchify":"^3.9.0"},"dependencies":{"vega":"^3.0.0-beta.32","vega-lite":"^2.0.0-beta.3","d3-selection":"^1.1.0","vega-schema-url-parser":"^1.0.0-beta.2"},"scripts":{"deploy":"npm run lint && scripts/deploy.sh","lint":"eslint src/","build":"browserify src/embed.js -t browserify-shim -d -s vega.embed > vega-embed.js","postbuild":"uglifyjs vega-embed.js -cm > vega-embed.min.js","watch":"watchify src/embed.js -t browserify-shim -v -d -s vega.embed -o vega-embed.js"},"browserify-shim":{"vega":"global:vega","vega-lite":"global:vl"},"gitHead":"26c3d20a0caf66c1dbebe6a7b3f57f06b64d88af","bugs":{"url":"https://github.com/vega/vega-embed/issues"},"homepage":"https://github.com/vega/vega-embed#readme","_id":"vega-embed@3.0.0-beta.16","_shasum":"64f9b29ea2b57570c057233bfed101c1a833c4b7","_from":".","_npmVersion":"4.2.0","_nodeVersion":"8.0.0","_npmUser":{"name":"domoritz","email":"domoritz@gmail.com"},"dist":{"shasum":"64f9b29ea2b57570c057233bfed101c1a833c4b7","tarball":"https://registry.npmjs.org/vega-embed/-/vega-embed-3.0.0-beta.16.tgz"},"maintainers":[{"name":"domoritz","email":"domoritz@gmail.com"},{"name":"jheer","email":"jeffrey.heer@gmail.com"}],"_npmOperationalInternal":{"host":"s3://npm-registry-packages","tmp":"tmp/vega-embed-3.0.0-beta.16.tgz_1496283801797_0.026569746434688568"},"directories":{}},"3.0.0-beta.17":{"name":"vega-embed","version":"3.0.0-beta.17","description":"Publish Vega visualizations as embedded web components.","keywords":["vega","data","visualization","component","embed"],"repository":{"type":"git","url":"git+ssh://git@github.com/vega/vega-embed.git"},"author":{"name":"UW Interactive Data Lab","url":"http://idl.cs.washington.edu"},"contributors":[{"name":"Jeffrey Heer","url":"https://homes.cs.washington.edu/~jheer/"},{"name":"Arvind Satyanarayan","url":"http://arvindsatya.com"},{"name":"Younghoon Kim"},{"name":"Dominik Moritz","url":"https://www.domoritz.de"}],"license":"BSD-3-Clause","main":"src/embed.js","devDependencies":{"browserify":"^14.4.0","browserify-shim":"^3.8.14","eslint":"^3.19.0","uglify-js":"^3.0.13","watchify":"^3.9.0"},"dependencies":{"vega":"^3.0.0-beta.32","vega-lite":"^2.0.0-beta.3","d3-selection":"^1.1.0","vega-schema-url-parser":"^1.0.0-beta.2"},"scripts":{"deploy":"npm run lint && scripts/deploy.sh","lint":"eslint src/","build":"browserify src/embed.js -t browserify-shim -d -s vega.embed > vega-embed.js","postbuild":"uglifyjs vega-embed.js -cm > vega-embed.min.js","watch":"watchify src/embed.js -t browserify-shim -v -d -s vega.embed -o vega-embed.js"},"browserify-shim":{"vega":"global:vega","vega-lite":"global:vl"},"gitHead":"3026b6503d717911f2addaac3144b4f87c48345a","bugs":{"url":"https://github.com/vega/vega-embed/issues"},"homepage":"https://github.com/vega/vega-embed#readme","_id":"vega-embed@3.0.0-beta.17","_npmVersion":"5.0.1","_nodeVersion":"8.0.0","_npmUser":{"name":"domoritz","email":"domoritz@gmail.com"},"dist":{"integrity":"sha512-suYXiPIHnmRO9pSozScZNF/H1vNEKDYDV67gCPnrt2Szcu5RFztFVxjEz1CFt8et57oa0VbTvpLLUUmJia0b2g==","shasum":"990cfc7f8f404a5beec2a0574a870f222539c2ad","tarball":"https://registry.npmjs.org/vega-embed/-/vega-embed-3.0.0-beta.17.tgz"},"maintainers":[{"name":"domoritz","email":"domoritz@gmail.com"},{"name":"jheer","email":"jeffrey.heer@gmail.com"}],"_npmOperationalInternal":{"host":"s3://npm-registry-packages","tmp":"tmp/vega-embed-3.0.0-beta.17.tgz_1496607781711_0.11546642333269119"},"directories":{}},"3.0.0-beta.18":{"name":"vega-embed","version":"3.0.0-beta.18","description":"Publish Vega visualizations as embedded web components.","keywords":["vega","data","visualization","component","embed"],"repository":{"type":"git","url":"git+ssh://git@github.com/vega/vega-embed.git"},"author":{"name":"UW Interactive Data Lab","url":"http://idl.cs.washington.edu"},"contributors":[{"name":"Jeffrey Heer","url":"https://homes.cs.washington.edu/~jheer/"},{"name":"Arvind Satyanarayan","url":"http://arvindsatya.com"},{"name":"Younghoon Kim"},{"name":"Dominik Moritz","url":"https://www.domoritz.de"}],"license":"BSD-3-Clause","main":"src/embed.js","devDependencies":{"browserify":"^14.4.0","browserify-shim":"^3.8.14","eslint":"^3.19.0","uglify-js":"^3.0.13","watchify":"^3.9.0"},"dependencies":{"vega":"^3.0.0-beta.34","vega-lite":"^2.0.0-beta.4","d3-selection":"^1.1.0","vega-schema-url-parser":"^1.0.0-beta.2"},"scripts":{"deploy":"npm run lint && scripts/deploy.sh","lint":"eslint src/","build":"browserify src/embed.js -t browserify-shim -d -s vega.embed > vega-embed.js","postbuild":"uglifyjs vega-embed.js -cm > vega-embed.min.js","watch":"watchify src/embed.js -t browserify-shim -v -d -s vega.embed -o vega-embed.js"},"browserify-shim":{"vega":"global:vega","vega-lite":"global:vl"},"gitHead":"70759bf413c43cde0f22f42b65d31b81471421b3","bugs":{"url":"https://github.com/vega/vega-embed/issues"},"homepage":"https://github.com/vega/vega-embed#readme","_id":"vega-embed@3.0.0-beta.18","_npmVersion":"5.0.1","_nodeVersion":"8.0.0","_npmUser":{"name":"domoritz","email":"domoritz@gmail.com"},"dist":{"integrity":"sha512-zWYpyKM5nekN46gMb0QZrYEkph5xFaHlyE+5XjolMiB1JWPEZTTvBgvAc1YPKmF/JZ1nSFkMAa8pJ0isaKXBLQ==","shasum":"a3218e69e82ed158fdd3b6c68d1a3d67b23fdb87","tarball":"https://registry.npmjs.org/vega-embed/-/vega-embed-3.0.0-beta.18.tgz"},"maintainers":[{"name":"domoritz","email":"domoritz@gmail.com"},{"name":"jheer","email":"jeffrey.heer@gmail.com"}],"_npmOperationalInternal":{"host":"s3://npm-registry-packages","tmp":"tmp/vega-embed-3.0.0-beta.18.tgz_1497125834374_0.31590487575158477"},"directories":{}},"3.0.0-beta.19":{"name":"vega-embed","version":"3.0.0-beta.19","description":"Publish Vega visualizations as embedded web components.","keywords":["vega","data","visualization","component","embed"],"repository":{"type":"git","url":"git+ssh://git@github.com/vega/vega-embed.git"},"author":{"name":"UW Interactive Data Lab","url":"http://idl.cs.washington.edu"},"contributors":[{"name":"Jeffrey Heer","url":"https://homes.cs.washington.edu/~jheer/"},{"name":"Arvind Satyanarayan","url":"http://arvindsatya.com"},{"name":"Younghoon Kim"},{"name":"Dominik Moritz","url":"https://www.domoritz.de"},{"name":"Yuri Astrakhan","email":"YuriAstrakhan@gmail.com"}],"license":"BSD-3-Clause","main":"src/embed.js","devDependencies":{"browserify":"^14.4.0","browserify-shim":"^3.8.14","eslint":"^3.19.0","uglify-es":"^3.0.15","watchify":"^3.9.0"},"dependencies":{"vega":"^3.0.0-beta.38","vega-lite":"^2.0.0-beta.4","d3-selection":"^1.1.0","vega-schema-url-parser":"^1.0.0-beta.2"},"scripts":{"deploy":"npm run lint && scripts/deploy.sh","lint":"eslint src/","build":"browserify src/embed.js -t browserify-shim -d -s vega.embed > vega-embed.js","postbuild":"uglifyjs vega-embed.js -cm > vega-embed.min.js","watch":"watchify src/embed.js -t browserify-shim -v -d -s vega.embed -o vega-embed.js"},"browserify-shim":{"vega":"global:vega","vega-lite":"global:vl"},"gitHead":"96823d8d19c947a19e165f71dd07fff439ceef17","bugs":{"url":"https://github.com/vega/vega-embed/issues"},"homepage":"https://github.com/vega/vega-embed#readme","_id":"vega-embed@3.0.0-beta.19","_npmVersion":"5.0.3","_nodeVersion":"8.1.2","_npmUser":{"name":"domoritz","email":"domoritz@gmail.com"},"dist":{"integrity":"sha512-63Q1YSiFENBapeXBjVkFnP4+8O6wH5gfD6gNi7gbW9N3Ay7pPzV4t2WbigxgLWmIpGNOnQQ5qq6J24ugni9nSA==","shasum":"c68dec612154839e784c18116b9680a1d695fbdf","tarball":"https://registry.npmjs.org/vega-embed/-/vega-embed-3.0.0-beta.19.tgz"},"maintainers":[{"name":"domoritz","email":"domoritz@gmail.com"},{"name":"jheer","email":"jeffrey.heer@gmail.com"}],"_npmOperationalInternal":{"host":"s3://npm-registry-packages","tmp":"tmp/vega-embed-3.0.0-beta.19.tgz_1498267784945_0.1659002078231424"},"directories":{}},"3.0.0-beta.20":{"name":"vega-embed","version":"3.0.0-beta.20","description":"Publish Vega visualizations as embedded web components.","keywords":["vega","data","visualization","component","embed"],"repository":{"type":"git","url":"git+ssh://git@github.com/vega/vega-embed.git"},"author":{"name":"UW Interactive Data Lab","url":"http://idl.cs.washington.edu"},"contributors":[{"name":"Jeffrey Heer","url":"https://homes.cs.washington.edu/~jheer/"},{"name":"Arvind Satyanarayan","url":"http://arvindsatya.com"},{"name":"Younghoon Kim"},{"name":"Dominik Moritz","url":"https://www.domoritz.de"},{"name":"Yuri Astrakhan","email":"YuriAstrakhan@gmail.com"}],"license":"BSD-3-Clause","main":"src/embed.js","devDependencies":{"browserify":"^14.4.0","browserify-shim":"^3.8.14","eslint":"^4.3.0","uglify-es":"^3.0.27","watchify":"^3.9.0"},"dependencies":{"vega":"^3.0.0-rc5","vega-lite":"^2.0.0-beta.11","compare-versions":"^3.0.1","d3-selection":"^1.1.0","vega-schema-url-parser":"^1.0.0-beta.2"},"scripts":{"deploy":"npm run lint && scripts/deploy.sh","lint":"eslint src/","build":"browserify src/embed.js -t browserify-shim -d -s vega.embed > vega-embed.js","postbuild":"uglifyjs vega-embed.js -cm > vega-embed.min.js","watch":"watchify src/embed.js -t browserify-shim -v -d -s vega.embed -o vega-embed.js"},"browserify-shim":{"vega":"global:vega","vega-lite":"global:vl"},"gitHead":"d8463666cbf06afedfb531565d81f048d02d7c6e","bugs":{"url":"https://github.com/vega/vega-embed/issues"},"homepage":"https://github.com/vega/vega-embed#readme","_id":"vega-embed@3.0.0-beta.20","_npmVersion":"5.3.0","_nodeVersion":"8.2.1","_npmUser":{"name":"domoritz","email":"domoritz@gmail.com"},"dist":{"integrity":"sha512-vZkp0M+rp46oek8njPAmaX8g8TyE8eDpdyccov2Xqh+vC52BcSdDtBzdYf04LSj9ZbDwg4fL2YWZBa3WByaPuQ==","shasum":"66b228d937256a823dd5e9dd6945d8159b34beb0","tarball":"https://registry.npmjs.org/vega-embed/-/vega-embed-3.0.0-beta.20.tgz"},"maintainers":[{"name":"domoritz","email":"domoritz@gmail.com"},{"name":"jheer","email":"jeffrey.heer@gmail.com"}],"_npmOperationalInternal":{"host":"s3://npm-registry-packages","tmp":"tmp/vega-embed-3.0.0-beta.20.tgz_1501909485828_0.24796893843449652"},"directories":{}}},"readme":"# Vega-Embed\n\n[![npm version](https://img.shields.io/npm/v/vega-embed.svg)](https://www.npmjs.com/package/vega-embed)\n\nThe [Vega-Embed](http://github.com/vega/vega-embed) module provides advanced support for embedding interactive Vega views into web pages. Current version supports only Vega 3 / Vega-Lite 2. The primary features include:\n\n- Load Vega/Vega-Lite specs from source text, parsed JSON, or URLs.\n- Add action links such as \"View Source\" and \"Open in Vega Editor\".\n\n\n_As Vega 3's `signal` supports [bind](https://github.com/vega/vega/blob/master/PORTING_GUIDE.md#scales), the `parameter` property from the [older version of Vega-Embed](https://github.com/vega/vega-embed/releases/tag/v2.2.0) is now deprecated._\n\n## Basic Example\n\nYou can import Vega-Embed from a local copy or (as shown below) [from CDNJS](https://cdnjs.com/libraries/vega-embed). Please replace `[VERSION]` with the correct [Vega](https://cdnjs.com/libraries/vega), [Vega-Lite](https://cdnjs.com/libraries/vega), and [Vega-Embed](https://cdnjs.com/libraries/vega-embed) versions.\n\n```html\n<!DOCTYPE html>\n<html>\n<head>\n  <!-- Import Vega 3 & Vega-Lite 2 js (does not have to be from cdn) -->\n  <script src=\"https://cdnjs.cloudflare.com/ajax/libs/vega/[VERSION]/vega.js\"></script>\n  <script src=\"https://cdnjs.cloudflare.com/ajax/libs/vega-lite/[VERSION]/vega-lite.js\"></script>\n  <!-- Import vega-embed -->\n  <script src=\"https://cdnjs.cloudflare.com/ajax/libs/vega-embed/[VERSION]/vega-embed.js\"></script>\n</head>\n<body>\n\n<div id=\"vis\"></div>\n\n<script type=\"text/javascript\">\n  var spec = \"https://raw.githubusercontent.com/vega/vega/master/docs/examples/bar-chart.vg.json\";\n  vega.embed('#vis', spec);\n</script>\n</body>\n</html>\n```\n\n\n## API Reference\n\n<a href=\"#embed\" name=\"embed\">#</a>\nvega.<b>embed</b>(<i>el</i>, <i>embed_spec</i>[, <i>opt</i>])\n[<>](https://github.com/vega/vega-embed/blob/master/src/embed.js \"Source\")\n\nReturns a [Promise](https://developer.mozilla.org/en-US/docs/Web/JavaScript/Reference/Global_Objects/Promise)* that resolves to the instantiated [Vega `View` instance](https://github.com/vega/vega-view#vega-view) and a copy of the parsed JSON Vega spec. The `embed` function accepts the following arguments:\n\n| Property| Type       | Description    |\n| :------ | :--------- | :------------- |\n| `el`      |  String  | A DOM element or CSS selector indicating the element on the page in which to add the embedded view. |\n| `spec`    | String / Object | _String_ : A URL string** from which to load the Vega specification. <br> _Object_ :  The Vega/Vega-Lite specification as a parsed JSON object. |\n| `opt`   | Object  | _(Optional)_ A JavaScript object containing options for embedding. |\n\n*_Internet Explorer does not support [the ES6 Promise](https://developer.mozilla.org/en-US/docs/Web/JavaScript/Reference/Global_Objects/Promise) feature. To make it work correctly, please follow [the instructions on the Vega website](https://vega.github.io/vega/usage/#ie)._\n\n**_This URL will be subject to standard browser security restrictions. Typically this URL will point to a file on the same host and port number as the web page itself._\n\n### Vega Embed `opt` Specification Reference\n\n```js\nvar opt = {\n  \"mode\": ...,\n  \"renderer\" : ...,\n  \"onBeforeParse\" : ...,\n  \"logLevel\" : ...,\n  \"width\" : ...,\n  \"height\" : ...,\n  \"padding\" : ...,\n  \"actions\" : ...,\n  \"config\"  : ...,\n  \"editorUrl\": ...,\n  \"sourceHeader\" : ...,\n  \"sourceFooter\": ...\n}\n```\n\n| Property | Type             | Description    |\n| :------- | :--------------- | :------------- |\n| `mode`        | String        | If specified, tells Vega-Embed to parse the spec as `vega` or `vega-lite`. Vega-Embed will parse the [`$schema` url](https://github.com/vega/schema) if the mode is not specified. Vega-Embed will default to `vega` if neither `mode`, nor `$schema` are specified. |\n| `renderer`    | String        | The renderer to use for the view. One of `\"canvas\"` (default) or `\"svg\"`. See [Vega docs](https://vega.github.io/vega/docs/api/view/#view_renderer) for details. |\n|`onBeforeParse`| Function      | Modifies the spec before being parsed.|\n| `logLevel`    | Level         | Sets the current log level. See [Vega docs](https://vega.github.io/vega/docs/api/view/#view_logLevel) for details. |\n| `width`       | Number        | Sets the view width in pixels. See [Vega docs](https://vega.github.io/vega/docs/api/view/#view_width) for details. Note that Vega-Lite overrides this option. |\n| `height`      | Number        | Sets the view height in pixels. See [Vega docs](https://vega.github.io/vega/docs/api/view/#view_height) for details. Note that Vega-Lite overrides this option. |\n| `padding`     | Object        | Sets the view padding in pixels. See [Vega docs](https://vega.github.io/vega/docs/api/view/#view_padding) for details. |\n| `actions`     | Boolean / Object       | Determines if action links (\"Export as PNG/SVG\", \"View Source\", \"Open in Vega Editor\") are included with the embedded view. If the value is `true` (default), all action links will be shown and none if the value is `false`.  This property can take a key-value mapping object that maps keys (`export`, `source`, `editor`) to boolean values for determining if each action link should be shown.  Unspecified keys will be `true` by default.  For example, if `actions` is `{export: false, source: true}`, the embedded visualization will have two links  \"View Source\" and \"Open in Vega Editor\".        |\n| `config`      | String / Object | _String_ : A URL string** from which to load a [Vega](https://vega.github.io/vega/docs/config/)/[Vega-Lite](https://vega.github.io/vega-lite/docs/config.html) configuration file. <br> _Object_ : A Vega/Vega-Lite configuration as a parsed JSON object to override the [default configuration options](https://github.com/vega/vega-parser/blob/master/src/config.js) or [specify a theme](https://github.com/vega/vega-parser#configuration-reference). |\n| `viewConfig`  | Object | Options passed to the view constructor. Details are in the [Vega documentation](https://vega.github.io/vega/docs/api/view/#view-construction). |\n| `editorUrl`    | String   | The URL at which to open embedded Vega specs in a Vega editor. Defaults to `\"http://vega.github.io/editor/\"`. Internally, Vega-Embed uses [HTML5 postMessage](https://developer.mozilla.org/en-US/docs/Web/API/Window/postMessage) to pass the specification information to the editor. |\n| `sourceHeader` | String   | HTML to inject into the `` tag of the page generated by the \"View Source\" action link. For example, this can be used to add code for [syntax highlighting](https://highlightjs.org/). |\n| `sourceFooter` | String   | HTML to inject into the end of the page generated by the \"View Source\" action link. The text will be added immediately before the closing `` tag. |\n\n**_This URL will be subject to standard browser security restrictions. Typically this URL will point to a file on the same host and port number as the web page itself._\n\n<a href=\"#embed.config\" name=\"embed.config\">#</a>\nvega.embed.<b>config</b>\n[<>](https://github.com/vega/vega-embed/blob/master/src/embed.js \"Source\")\n\n## Build Process\n\nTo build `vega-embed.js` and view the test examples, you must have [npm](https://www.npmjs.com/) installed.\n\n1. Run `npm install` in the Vega-Embed folder to install dependencies.\n2. Run `npm run build`. This will invoke [browserify](http://browserify.org/) to bundle the source files into `vega-embed.js`, and then [uglify-js](http://lisperator.net/uglifyjs/) to create the minified `vega-embed.min.js`.\n3. Run a local webserver (e.g., `python -m SimpleHTTPServer 8000`) in the Vega-Embed folder and then point your web browser at the test page (e.g., `http://localhost:8000/test.html`).\n","maintainers":[{"name":"domoritz","email":"domoritz@gmail.com"},{"name":"jheer","email":"jeffrey.heer@gmail.com"}],"time":{"modified":"2017-08-05T05:04:46.077Z","created":"2015-08-19T03:36:03.075Z","1.0.0":"2015-08-19T03:36:03.075Z","1.0.1":"2015-08-19T03:44:28.441Z","1.0.2":"2015-08-19T05:08:57.645Z","1.0.3":"2015-08-25T22:53:02.617Z","1.0.4":"2015-08-27T20:13:12.414Z","1.0.5":"2015-08-28T21:48:29.802Z","1.0.6":"2015-08-31T00:39:02.193Z","1.0.7":"2015-08-31T05:43:10.550Z","1.0.8":"2015-09-09T16:56:39.758Z","1.0.9":"2015-09-09T18:42:35.367Z","2.0.0":"2015-12-15T22:56:49.098Z","2.1.0":"2016-03-01T16:44:06.859Z","2.2.0":"2016-06-21T18:08:31.527Z","3.0.0-beta.0":"2017-02-13T16:21:45.748Z","3.0.0-beta.1":"2017-02-16T17:52:34.792Z","3.0.0-beta.2":"2017-02-26T00:49:51.650Z","3.0.0-beta.3":"2017-02-26T01:00:55.468Z","3.0.0-beta.4":"2017-02-26T01:05:42.298Z","3.0.0-beta.5":"2017-03-02T00:38:03.542Z","3.0.0-beta.6":"2017-03-10T22:20:28.497Z","3.0.0-beta.7":"2017-03-28T18:39:12.013Z","3.0.0-beta.8":"2017-04-11T01:25:56.664Z","3.0.0-beta.9":"2017-04-11T01:39:43.032Z","3.0.0-beta.10":"2017-04-14T00:20:54.386Z","3.0.0-beta.11":"2017-04-25T02:06:45.782Z","3.0.0-beta.12":"2017-04-30T18:32:53.116Z","3.0.0-beta.13":"2017-04-30T18:39:09.902Z","3.0.0-beta.14":"2017-04-30T18:46:09.016Z","3.0.0-beta.15":"2017-05-30T21:02:57.837Z","3.0.0-beta.16":"2017-06-01T02:23:22.020Z","3.0.0-beta.17":"2017-06-04T20:23:01.904Z","3.0.0-beta.18":"2017-06-10T20:17:14.636Z","3.0.0-beta.19":"2017-06-24T01:29:45.066Z","3.0.0-beta.20":"2017-08-05T05:04:46.077Z"},"homepage":"https://github.com/vega/vega-embed#readme","keywords":["vega","data","visualization","component","embed"],"repository":{"type":"git","url":"git+ssh://git@github.com/vega/vega-embed.git"},"author":{"name":"UW Interactive Data Lab","url":"http://idl.cs.washington.edu"},"bugs":{"url":"https://github.com/vega/vega-embed/issues"},"license":"BSD-3-Clause","readmeFilename":"README.md","contributors":[{"name":"Jeffrey Heer","url":"https://homes.cs.washington.edu/~jheer/"},{"name":"Arvind Satyanarayan","url":"http://arvindsatya.com"},{"name":"Younghoon Kim"},{"name":"Dominik Moritz","url":"https://www.domoritz.de"},{"name":"Yuri Astrakhan","email":"YuriAstrakhan@gmail.com"}],"_attachments":{},"_etag":"W/\"598551ee-127e5\"","_lastModified":"Sat, 05 Aug 2017 05:04:46 GMT","_cached":true}